pymcmcstat/MCMC.py
pymcmcstat/ParallelMCMC.py
pymcmcstat/__init__.py
pymcmcstat/propagation.py
pymcmcstat/chain/ChainProcessing.py
pymcmcstat/chain/ChainStatistics.py
pymcmcstat/chain/__init__.py
pymcmcstat/plotting/MCMCPlotting.py
pymcmcstat/plotting/PredictionIntervals.py
pymcmcstat/plotting/__init__.py
pymcmcstat/plotting/utilities.py
pymcmcstat/procedures/CovarianceProcedures.py
pymcmcstat/procedures/ErrorVarianceEstimator.py
pymcmcstat/procedures/PriorFunction.py
pymcmcstat/procedures/SumOfSquares.py
pymcmcstat/procedures/__init__.py
pymcmcstat/samplers/Adaptation.py
pymcmcstat/samplers/DelayedRejection.py
pymcmcstat/samplers/Metropolis.py
pymcmcstat/samplers/SamplingMethods.py
pymcmcstat/samplers/__init__.py
pymcmcstat/samplers/utilities.py
pymcmcstat/settings/DataStructure.py
pymcmcstat/settings/ModelParameters.py
pymcmcstat/settings/ModelSettings.py
pymcmcstat/settings/SimulationOptions.py
pymcmcstat/settings/__init__.py
pymcmcstat/structures/ParameterSet.py
pymcmcstat/structures/ResultsStructure.py
pymcmcstat/structures/__init__.py
pymcmcstat/utilities/NumpyEncoder.py
pymcmcstat/utilities/__init__.py
pymcmcstat/utilities/general.py
pymcmcstat/utilities/progressbar.py
test/__init__.py
test/general_functions.py
test/test_MCMC.py
test/test_ParallelMCMC.py
test/test_init.py
test/test_propagation.py
test/chain/__init__.py
test/chain/test_ChainProcessing.py
test/chain/test_ChainStatistics.py
test/plotting/__init__.py
test/plotting/test_MCMCPlotting.py
test/plotting/test_PredictionIntervals.py
test/plotting/test_utilities.py
test/procedures/__init__.py
test/procedures/test_CovarianceProcedures.py
test/procedures/test_ErrorVarianceEstimator.py
test/procedures/test_PriorFunction.py
test/procedures/test_SumOfSquares.py
test/samplers/__init__.py
test/samplers/test_Adaptation.py
test/samplers/test_DelayedRejection.py
test/samplers/test_Metropolis.py
test/samplers/test_SamplingMethods.py
test/samplers/test_utilities.py
test/settings/__init__.py
pymcmcstat-1.9.1.dist-info/LICENSE.txt
pymcmcstat-1.9.1.dist-info/METADATA
pymcmcstat-1.9.1.dist-info/WHEEL
pymcmcstat-1.9.1.dist-info/top_level.txt
pymcmcstat-1.9.1.dist-info/RECORD
