Metadata-Version: 2.1
Name: pymcmcstat
Version: 1.9.1
Summary: A library to perform MCMC simulations using DRAM
Home-page: https://github.com/prmiles/pymcmcstat
Author: Paul Miles
Author-email: prmiles@ncsu.edu
License: MIT
Download-URL: https://github.com/prmiles/pymcmcstat
Platform: UNKNOWN
Classifier: License :: OSI Approved :: MIT License
Classifier: Natural Language :: English
Classifier: Operating System :: MacOS :: MacOS X
Classifier: Operating System :: POSIX :: Linux
Classifier: Programming Language :: Python :: 3.6
Classifier: Framework :: IPython
Classifier: Intended Audience :: Science/Research
Classifier: Topic :: Scientific/Engineering
Provides-Extra: docs
Provides-Extra: plotting
